files_folders_with_timestamp/LICENSE
files_folders_with_timestamp/README.MD
files_folders_with_timestamp/__init__.py
files_folders_with_timestamp/requirements.txt
files_folders_with_timestamp/thirdparty.json
files_folders_with_timestamp-0.10.dist-info/LICENSE.rst
files_folders_with_timestamp-0.10.dist-info/METADATA
files_folders_with_timestamp-0.10.dist-info/WHEEL
files_folders_with_timestamp-0.10.dist-info/top_level.txt
files_folders_with_timestamp-0.10.dist-info/RECORD
